README.md
setup.cfg
setup.py
postal/__init__.py
postal/dedupe.py
postal/expand.py
postal/near_dupe.py
postal/normalize.py
postal/parser.py
postal/pydedupe.c
postal/pyexpand.c
postal/pyneardupe.c
postal/pynormalize.c
postal/pyparser.c
postal/pytokenize.c
postal/pytokentypes.c
postal/pyutils.c
postal/pyutils.h
postal/token_types.py
postal/tokenize.py
postal.egg-info/PKG-INFO
postal.egg-info/SOURCES.txt
postal.egg-info/dependency_links.txt
postal.egg-info/not-zip-safe
postal.egg-info/requires.txt
postal.egg-info/top_level.txt
postal/tests/__init__.py
postal/tests/test_expand.py
postal/tests/test_near_dupes.py
postal/tests/test_parser.py
postal/utils/__init__.py
postal/utils/encoding.py
postal/utils/enum.py
postal/utils/omitted.py