Metadata-Version: 1.1
Name: postal
Version: 1.1.6
Summary: Python bindings to libpostal for fast international address parsing/normalization
Home-page: https://github.com/openvenues/pypostal
Author: mapzen.com
Author-email: pelias@mapzen.com
License: MIT License
Download-URL: https://github.com/openvenues/pypostal/tarball/1.1.6
Platform: UNKNOWN
Classifier: Intended Audience :: Developers
Classifier: Intended Audience :: Information Technology
Classifier: License :: OSI Approved :: MIT License
Classifier: Programming Language :: C
Classifier: Programming Language :: Python :: 2
Classifier: Programming Language :: Python :: 2.7
Classifier: Programming Language :: Python :: 3
Classifier: Programming Language :: Python :: 3.4
Classifier: Programming Language :: Python :: 3.5
Classifier: Operating System :: MacOS :: MacOS X
Classifier: Operating System :: POSIX :: Linux
Classifier: Topic :: Text Processing :: Linguistic
Classifier: Topic :: Scientific/Engineering :: GIS
Classifier: Topic :: Internet :: WWW/HTTP :: Indexing/Search
Classifier: Topic :: Software Development :: Libraries :: Python Modules
